hello.py
hellobalazs.py
hellobalazs-0.0.2.dist-info/METADATA
hellobalazs-0.0.2.dist-info/RECORD
hellobalazs-0.0.2.dist-info/WHEEL
hellobalazs-0.0.2.dist-info/top_level.txt
